{
  "author": {
    "name": "",
    "email": "",
    "url": ""
  },
  "date": "YYYY-MM-DD",
  "os": {
    "name": "",
    "version": ""
  },
  "server": {
    "manufacturer": "",
    "product": ""
  },
  "gnss": {
    "manufacturer": "",
    "product": ""
  },
  "daemon": [
    {
      "name": "chrony",
      "version": "4.6.1",
      "accuracy": 0.01
    },
    {
      "name": "NTPsec",
      "version": "1.2.3",
      "accuracy": 0.01
    },
    {
      "name": "ntp",
      "version": "4.2.8",
      "accuracy": 0.01
    }
  ],
  "url": ""
}
